{"stock_code":"078340","stock_name":"컴투스","name_eng":"","sector":"","ceo":"","homepage":"","established":"","latest_per":null,"latest_pbr":null,"latest_roe":null,"latest_debt_ratio":null,"latest_ref_price":null,"fin_period":"","filing_count":6,"first_seen":"20171019","last_seen":"20200716","latest_stake_pct":3.95,"filings":[{"ref_date":"20171019","obligation_date":"20171019","feed_date":"2018-01-05","change_type":"신규","stake_pct":5.01,"stake_prev_pct":null,"stake_change":null,"ref_price":null,"total_buy_amount":0,"total_sell_amount":0,"net_amount":0,"trade_count":0,"dart_link":"https://dart.fss.or.kr/dsaf001/main.do?rcpNo=20180105000069","trades":[]},{"ref_date":"20180530","obligation_date":"20180530","feed_date":"2018-07-04","change_type":"재진입","stake_pct":6.03,"stake_prev_pct":null,"stake_change":null,"ref_price":null,"total_buy_amount":0,"total_sell_amount":0,"net_amount":0,"trade_count":0,"dart_link":"https://dart.fss.or.kr/dsaf001/main.do?rcpNo=20180704000205","trades":[],"_original_change_type":"신규"},{"ref_date":"20190219","obligation_date":"20190219","feed_date":"2019-04-02","change_type":"재진입","stake_pct":7.03,"stake_prev_pct":null,"stake_change":null,"ref_price":null,"total_buy_amount":0,"total_sell_amount":0,"net_amount":0,"trade_count":0,"dart_link":"https://dart.fss.or.kr/dsaf001/main.do?rcpNo=20190402000593","trades":[],"_original_change_type":"신규"},{"ref_date":"20200302","obligation_date":"20200302","feed_date":"2020-04-03","change_type":"재진입","stake_pct":5.88,"stake_prev_pct":null,"stake_change":null,"ref_price":null,"total_buy_amount":0,"total_sell_amount":0,"net_amount":0,"trade_count":0,"dart_link":"https://dart.fss.or.kr/dsaf001/main.do?rcpNo=20200403000514","trades":[],"_original_change_type":"신규"},{"ref_date":"20200515","obligation_date":"20200515","feed_date":"2020-07-03","change_type":"재진입","stake_pct":4.84,"stake_prev_pct":null,"stake_change":null,"ref_price":null,"total_buy_amount":0,"total_sell_amount":0,"net_amount":0,"trade_count":0,"dart_link":"https://dart.fss.or.kr/dsaf001/main.do?rcpNo=20200703000161","trades":[],"_original_change_type":"신규"},{"ref_date":"20200828","obligation_date":"20200716","feed_date":"2020-10-06","change_type":"재진입","stake_pct":3.95,"stake_prev_pct":null,"stake_change":null,"ref_price":null,"total_buy_amount":0,"total_sell_amount":0,"net_amount":0,"trade_count":0,"dart_link":"https://dart.fss.or.kr/dsaf001/main.do?rcpNo=20201006000081","trades":[],"_original_change_type":"신규"}]}