{"stock_code":"086390","stock_name":"유니테스트","name_eng":"","sector":"","ceo":"","homepage":"","established":"","latest_per":null,"latest_pbr":null,"latest_roe":null,"latest_debt_ratio":null,"latest_ref_price":null,"fin_period":"","filing_count":7,"first_seen":"20190805","last_seen":"20200708","latest_stake_pct":4.02,"filings":[{"ref_date":"20190805","obligation_date":"20190805","feed_date":"2019-10-04","change_type":"신규","stake_pct":5.37,"stake_prev_pct":null,"stake_change":null,"ref_price":null,"total_buy_amount":0,"total_sell_amount":0,"net_amount":0,"trade_count":0,"dart_link":"https://dart.fss.or.kr/dsaf001/main.do?rcpNo=20191004000085","trades":[]},{"ref_date":"20191120","obligation_date":"20191014","feed_date":"2020-01-06","change_type":"재진입","stake_pct":7.55,"stake_prev_pct":null,"stake_change":null,"ref_price":null,"total_buy_amount":0,"total_sell_amount":0,"net_amount":0,"trade_count":0,"dart_link":"https://dart.fss.or.kr/dsaf001/main.do?rcpNo=20200106000083","trades":[],"_original_change_type":"신규"},{"ref_date":"20200309","obligation_date":"20200309","feed_date":"2020-04-03","change_type":"재진입","stake_pct":8.61,"stake_prev_pct":null,"stake_change":null,"ref_price":null,"total_buy_amount":0,"total_sell_amount":0,"net_amount":0,"trade_count":0,"dart_link":"https://dart.fss.or.kr/dsaf001/main.do?rcpNo=20200403000457","trades":[],"_original_change_type":"신규"},{"ref_date":"20200514","obligation_date":"20200514","feed_date":"2020-07-03","change_type":"재진입","stake_pct":9.82,"stake_prev_pct":null,"stake_change":null,"ref_price":null,"total_buy_amount":0,"total_sell_amount":0,"net_amount":0,"trade_count":0,"dart_link":"https://dart.fss.or.kr/dsaf001/main.do?rcpNo=20200703000119","trades":[],"_original_change_type":"신규"},{"ref_date":"20200601","obligation_date":"20200601","feed_date":"2020-06-04","change_type":"재진입","stake_pct":10.27,"stake_prev_pct":null,"stake_change":null,"ref_price":null,"total_buy_amount":0,"total_sell_amount":0,"net_amount":0,"trade_count":0,"dart_link":"https://dart.fss.or.kr/dsaf001/main.do?rcpNo=20200604000026","trades":[],"_original_change_type":"신규"},{"ref_date":"20200629","obligation_date":"20200602","feed_date":"2020-07-06","change_type":"감소","stake_pct":9.55,"stake_prev_pct":10.27,"stake_change":-0.7199999999999989,"ref_price":null,"total_buy_amount":0,"total_sell_amount":0,"net_amount":0,"trade_count":0,"dart_link":"https://dart.fss.or.kr/dsaf001/main.do?rcpNo=20200706000052","trades":[]},{"ref_date":"20200820","obligation_date":"20200708","feed_date":"2020-10-06","change_type":"재진입","stake_pct":4.02,"stake_prev_pct":null,"stake_change":null,"ref_price":null,"total_buy_amount":0,"total_sell_amount":0,"net_amount":0,"trade_count":0,"dart_link":"https://dart.fss.or.kr/dsaf001/main.do?rcpNo=20201006000167","trades":[],"_original_change_type":"신규"}]}