{"stock_code":"222800","stock_name":"심텍","name_eng":"","sector":"","ceo":"","homepage":"","established":"","latest_per":null,"latest_pbr":null,"latest_roe":null,"latest_debt_ratio":null,"latest_ref_price":null,"fin_period":"","filing_count":10,"first_seen":"20200407","last_seen":"20240220","latest_stake_pct":4.26,"filings":[{"ref_date":"20200615","obligation_date":"20200407","feed_date":"2020-07-03","change_type":"신규","stake_pct":6.25,"stake_prev_pct":null,"stake_change":null,"ref_price":null,"total_buy_amount":0,"total_sell_amount":0,"net_amount":0,"trade_count":0,"dart_link":"https://dart.fss.or.kr/dsaf001/main.do?rcpNo=20200703000337","trades":[]},{"ref_date":"20200922","obligation_date":"20200819","feed_date":"2020-10-06","change_type":"재진입","stake_pct":6.19,"stake_prev_pct":null,"stake_change":null,"ref_price":null,"total_buy_amount":0,"total_sell_amount":0,"net_amount":0,"trade_count":0,"dart_link":"https://dart.fss.or.kr/dsaf001/main.do?rcpNo=20201006000146","trades":[],"_original_change_type":"신규"},{"ref_date":"20210331","obligation_date":"20210225","feed_date":"2021-04-05","change_type":"재진입","stake_pct":3.98,"stake_prev_pct":null,"stake_change":null,"ref_price":null,"total_buy_amount":0,"total_sell_amount":0,"net_amount":0,"trade_count":0,"dart_link":"https://dart.fss.or.kr/dsaf001/main.do?rcpNo=20210405001765","trades":[],"_original_change_type":"신규"},{"ref_date":"20210802","obligation_date":"20210802","feed_date":"2021-10-06","change_type":"재진입","stake_pct":5.08,"stake_prev_pct":null,"stake_change":null,"ref_price":null,"total_buy_amount":0,"total_sell_amount":0,"net_amount":0,"trade_count":0,"dart_link":"https://dart.fss.or.kr/dsaf001/main.do?rcpNo=20211006000196","trades":[],"_original_change_type":"신규"},{"ref_date":"20211015","obligation_date":"20211015","feed_date":"2022-01-05","change_type":"재진입","stake_pct":6.11,"stake_prev_pct":null,"stake_change":null,"ref_price":null,"total_buy_amount":0,"total_sell_amount":0,"net_amount":0,"trade_count":0,"dart_link":"https://dart.fss.or.kr/dsaf001/main.do?rcpNo=20220105000148","trades":[],"_original_change_type":"신규"},{"ref_date":"20220310","obligation_date":"20220310","feed_date":"2022-04-05","change_type":"재진입","stake_pct":7.2,"stake_prev_pct":null,"stake_change":null,"ref_price":null,"total_buy_amount":0,"total_sell_amount":0,"net_amount":0,"trade_count":0,"dart_link":"https://dart.fss.or.kr/dsaf001/main.do?rcpNo=20220405001505","trades":[],"_original_change_type":"신규"},{"ref_date":"20220602","obligation_date":"20220602","feed_date":"2022-07-05","change_type":"재진입","stake_pct":5.58,"stake_prev_pct":null,"stake_change":null,"ref_price":null,"total_buy_amount":0,"total_sell_amount":0,"net_amount":0,"trade_count":0,"dart_link":"https://dart.fss.or.kr/dsaf001/main.do?rcpNo=20220705000409","trades":[],"_original_change_type":"신규"},{"ref_date":"20220705","obligation_date":"20220705","feed_date":"2022-10-07","change_type":"재진입","stake_pct":4.52,"stake_prev_pct":null,"stake_change":null,"ref_price":null,"total_buy_amount":0,"total_sell_amount":0,"net_amount":0,"trade_count":0,"dart_link":"https://dart.fss.or.kr/dsaf001/main.do?rcpNo=20221007000090","trades":[],"_original_change_type":"신규"},{"ref_date":"20230920","obligation_date":"20230720","feed_date":"2023-10-05","change_type":"재진입","stake_pct":7.03,"stake_prev_pct":null,"stake_change":null,"ref_price":null,"total_buy_amount":0,"total_sell_amount":0,"net_amount":0,"trade_count":0,"dart_link":"https://dart.fss.or.kr/dsaf001/main.do?rcpNo=20231005000034","trades":[],"_original_change_type":"신규"},{"ref_date":"20240313","obligation_date":"20240220","feed_date":"2024-04-02","change_type":"재진입","stake_pct":4.26,"stake_prev_pct":null,"stake_change":null,"ref_price":null,"total_buy_amount":0,"total_sell_amount":0,"net_amount":0,"trade_count":0,"dart_link":"https://dart.fss.or.kr/dsaf001/main.do?rcpNo=20240402001828","trades":[],"_original_change_type":"신규"}]}