{"stock_code":"023160","stock_name":"태광","name_eng":"T. K. CORPORATION","sector":"금속","ceo":"","homepage":"www.tkbend.co.kr","established":"19820901","latest_per":15.66,"latest_pbr":1.56,"latest_roe":10.73,"latest_debt_ratio":10.63,"latest_ref_price":37750,"fin_period":"","filing_count":18,"first_seen":"20180130","last_seen":"20260309","latest_stake_pct":5.55,"filings":[{"ref_date":"20180130","obligation_date":"20180130","feed_date":"2018-04-04","change_type":"신규","stake_pct":5.07,"stake_prev_pct":null,"stake_change":null,"ref_price":null,"total_buy_amount":0,"total_sell_amount":0,"net_amount":0,"trade_count":0,"dart_link":"https://dart.fss.or.kr/dsaf001/main.do?rcpNo=20180404000322","trades":[]},{"ref_date":"20180412","obligation_date":"20180412","feed_date":"2018-07-04","change_type":"재진입","stake_pct":6.15,"stake_prev_pct":null,"stake_change":null,"ref_price":null,"total_buy_amount":0,"total_sell_amount":0,"net_amount":0,"trade_count":0,"dart_link":"https://dart.fss.or.kr/dsaf001/main.do?rcpNo=20180704000226","trades":[],"_original_change_type":"신규"},{"ref_date":"20180906","obligation_date":"20180906","feed_date":"2018-10-04","change_type":"재진입","stake_pct":5.08,"stake_prev_pct":null,"stake_change":null,"ref_price":null,"total_buy_amount":0,"total_sell_amount":0,"net_amount":0,"trade_count":0,"dart_link":"https://dart.fss.or.kr/dsaf001/main.do?rcpNo=20181004000235","trades":[],"_original_change_type":"신규"},{"ref_date":"20181107","obligation_date":"20181107","feed_date":"2019-01-04","change_type":"재진입","stake_pct":3.89,"stake_prev_pct":null,"stake_change":null,"ref_price":null,"total_buy_amount":0,"total_sell_amount":0,"net_amount":0,"trade_count":0,"dart_link":"https://dart.fss.or.kr/dsaf001/main.do?rcpNo=20190104000136","trades":[],"_original_change_type":"신규"},{"ref_date":"20200212","obligation_date":"20200212","feed_date":"2020-04-03","change_type":"재진입","stake_pct":5.01,"stake_prev_pct":null,"stake_change":null,"ref_price":null,"total_buy_amount":0,"total_sell_amount":0,"net_amount":0,"trade_count":0,"dart_link":"https://dart.fss.or.kr/dsaf001/main.do?rcpNo=20200403000164","trades":[],"_original_change_type":"신규"},{"ref_date":"20200911","obligation_date":"20200911","feed_date":"2020-10-06","change_type":"재진입","stake_pct":4.01,"stake_prev_pct":null,"stake_change":null,"ref_price":null,"total_buy_amount":0,"total_sell_amount":0,"net_amount":0,"trade_count":0,"dart_link":"https://dart.fss.or.kr/dsaf001/main.do?rcpNo=20201006000183","trades":[],"_original_change_type":"신규"},{"ref_date":"20220311","obligation_date":"20220311","feed_date":"2022-04-05","change_type":"재진입","stake_pct":5.0,"stake_prev_pct":null,"stake_change":null,"ref_price":null,"total_buy_amount":0,"total_sell_amount":0,"net_amount":0,"trade_count":0,"dart_link":"https://dart.fss.or.kr/dsaf001/main.do?rcpNo=20220405001831","trades":[],"_original_change_type":"신규"},{"ref_date":"20220524","obligation_date":"20220524","feed_date":"2022-07-05","change_type":"재진입","stake_pct":6.0,"stake_prev_pct":null,"stake_change":null,"ref_price":null,"total_buy_amount":0,"total_sell_amount":0,"net_amount":0,"trade_count":0,"dart_link":"https://dart.fss.or.kr/dsaf001/main.do?rcpNo=20220705000483","trades":[],"_original_change_type":"신규"},{"ref_date":"20220920","obligation_date":"20220920","feed_date":"2022-10-06","change_type":"재진입","stake_pct":7.01,"stake_prev_pct":null,"stake_change":null,"ref_price":null,"total_buy_amount":0,"total_sell_amount":0,"net_amount":0,"trade_count":0,"dart_link":"https://dart.fss.or.kr/dsaf001/main.do?rcpNo=20221006000558","trades":[],"_original_change_type":"신규"},{"ref_date":"20221116","obligation_date":"20221116","feed_date":"2023-01-03","change_type":"재진입","stake_pct":8.05,"stake_prev_pct":null,"stake_change":null,"ref_price":null,"total_buy_amount":0,"total_sell_amount":0,"net_amount":0,"trade_count":0,"dart_link":"https://dart.fss.or.kr/dsaf001/main.do?rcpNo=20230103000181","trades":[],"_original_change_type":"신규"},{"ref_date":"20230612","obligation_date":"20230612","feed_date":"2023-07-04","change_type":"재진입","stake_pct":7.04,"stake_prev_pct":null,"stake_change":null,"ref_price":null,"total_buy_amount":0,"total_sell_amount":0,"net_amount":0,"trade_count":0,"dart_link":"https://dart.fss.or.kr/dsaf001/main.do?rcpNo=20230704000208","trades":[],"_original_change_type":"신규"},{"ref_date":"20230904","obligation_date":"20230904","feed_date":"2023-10-05","change_type":"재진입","stake_pct":8.23,"stake_prev_pct":null,"stake_change":null,"ref_price":null,"total_buy_amount":0,"total_sell_amount":0,"net_amount":0,"trade_count":0,"dart_link":"https://dart.fss.or.kr/dsaf001/main.do?rcpNo=20231005000180","trades":[],"_original_change_type":"신규"},{"ref_date":"20240201","obligation_date":"20240115","feed_date":"2024-04-02","change_type":"재진입","stake_pct":5.04,"stake_prev_pct":null,"stake_change":null,"ref_price":null,"total_buy_amount":0,"total_sell_amount":0,"net_amount":0,"trade_count":0,"dart_link":"https://dart.fss.or.kr/dsaf001/main.do?rcpNo=20240402001357","trades":[],"_original_change_type":"신규"},{"ref_date":"20240517","obligation_date":"20240517","feed_date":"2024-07-02","change_type":"재진입","stake_pct":3.99,"stake_prev_pct":null,"stake_change":null,"ref_price":null,"total_buy_amount":0,"total_sell_amount":0,"net_amount":0,"trade_count":0,"dart_link":"https://dart.fss.or.kr/dsaf001/main.do?rcpNo=20240702000268","trades":[],"_original_change_type":"신규"},{"ref_date":"20250512","obligation_date":"20250401","feed_date":"2025-07-02","change_type":"재진입","stake_pct":3.73,"stake_prev_pct":null,"stake_change":null,"ref_price":null,"total_buy_amount":0,"total_sell_amount":0,"net_amount":0,"trade_count":0,"dart_link":"https://dart.fss.or.kr/dsaf001/main.do?rcpNo=20250702000052","trades":[],"_original_change_type":"신규"},{"ref_date":"20250710","obligation_date":"20250710","feed_date":"2025-10-01","change_type":"재진입","stake_pct":5.0,"stake_prev_pct":null,"stake_change":null,"ref_price":null,"total_buy_amount":0,"total_sell_amount":0,"net_amount":0,"trade_count":0,"dart_link":"https://dart.fss.or.kr/dsaf001/main.do?rcpNo=20251001000231","trades":[],"_original_change_type":"신규"},{"ref_date":"20260102","obligation_date":"20251229","feed_date":"2026-01-02","change_type":"증가","stake_pct":6.65,"stake_prev_pct":5.0,"stake_change":1.65,"ref_price":20950,"total_buy_amount":15704665650,"total_sell_amount":6165064900,"net_amount":9539600750,"trade_count":3,"dart_link":"https://dart.fss.or.kr/dsaf001/main.do?rcpNo=20260102000239","trades":[{"date":"20251010","reason":"Buy","shares_before":1325528,"shares_change":360512,"shares_after":1686040,"unit_price":21850,"note":"-","estimated":true},{"date":"20251023","reason":"Buy","shares_before":1686040,"shares_change":358237,"shares_after":2044277,"unit_price":21850,"note":"-","estimated":true},{"date":"20251229","reason":"Sell","shares_before":2044277,"shares_change":-282154,"shares_after":1762123,"unit_price":21850,"note":"-","estimated":true}]},{"ref_date":"","obligation_date":"20260309","feed_date":"2026-04-01","change_type":"감소","stake_pct":5.55,"stake_prev_pct":6.65,"stake_change":-1.1,"ref_price":37750,"total_buy_amount":0,"total_sell_amount":0,"net_amount":-9550502400,"trade_count":1,"dart_link":"https://dart.fss.or.kr/dsaf001/main.do?rcpNo=20260401004468","trades":[{"date":"20260309","reason":"Sell","shares_before":1762123,"shares_change":-327072,"shares_after":1435051,"unit_price":29200,"note":"","estimated":true}]}]}