{"stock_code":"031980","stock_name":"피에스케이홀딩스","name_eng":"","sector":"","ceo":"","homepage":"","established":"","latest_per":null,"latest_pbr":null,"latest_roe":null,"latest_debt_ratio":null,"latest_ref_price":null,"fin_period":"","filing_count":3,"first_seen":"20240422","last_seen":"20260303","latest_stake_pct":5.13,"filings":[{"ref_date":"20240422","obligation_date":"20240422","feed_date":"2024-07-02","change_type":"신규","stake_pct":5.06,"stake_prev_pct":null,"stake_change":null,"ref_price":null,"total_buy_amount":0,"total_sell_amount":0,"net_amount":0,"trade_count":0,"dart_link":"https://dart.fss.or.kr/dsaf001/main.do?rcpNo=20240702000160","trades":[]},{"ref_date":"20240703","obligation_date":"20240703","feed_date":"2024-10-07","change_type":"재진입","stake_pct":3.98,"stake_prev_pct":null,"stake_change":null,"ref_price":null,"total_buy_amount":0,"total_sell_amount":0,"net_amount":0,"trade_count":0,"dart_link":"https://dart.fss.or.kr/dsaf001/main.do?rcpNo=20241007000272","trades":[],"_original_change_type":"신규"},{"ref_date":"20260303","obligation_date":"20260303","feed_date":"2026-04-01","change_type":"재진입","stake_pct":5.13,"stake_prev_pct":null,"stake_change":null,"ref_price":null,"total_buy_amount":0,"total_sell_amount":0,"net_amount":0,"trade_count":0,"dart_link":"https://dart.fss.or.kr/dsaf001/main.do?rcpNo=20260401002332","trades":[],"_original_change_type":"신규"}]}