{"stock_code":"046890","stock_name":"서울반도체","name_eng":"","sector":"","ceo":"","homepage":"","established":"","latest_per":null,"latest_pbr":null,"latest_roe":null,"latest_debt_ratio":null,"latest_ref_price":null,"fin_period":"","filing_count":9,"first_seen":"20180523","last_seen":"20210721","latest_stake_pct":4.26,"filings":[{"ref_date":"20180523","obligation_date":"20180523","feed_date":"2018-07-04","change_type":"신규","stake_pct":5.05,"stake_prev_pct":null,"stake_change":null,"ref_price":null,"total_buy_amount":0,"total_sell_amount":0,"net_amount":0,"trade_count":0,"dart_link":"https://dart.fss.or.kr/dsaf001/main.do?rcpNo=20180704000106","trades":[]},{"ref_date":"20181119","obligation_date":"20181016","feed_date":"2019-01-04","change_type":"재진입","stake_pct":7.11,"stake_prev_pct":null,"stake_change":null,"ref_price":null,"total_buy_amount":0,"total_sell_amount":0,"net_amount":0,"trade_count":0,"dart_link":"https://dart.fss.or.kr/dsaf001/main.do?rcpNo=20190104000214","trades":[],"_original_change_type":"신규"},{"ref_date":"20190128","obligation_date":"20190128","feed_date":"2019-04-02","change_type":"재진입","stake_pct":8.12,"stake_prev_pct":null,"stake_change":null,"ref_price":null,"total_buy_amount":0,"total_sell_amount":0,"net_amount":0,"trade_count":0,"dart_link":"https://dart.fss.or.kr/dsaf001/main.do?rcpNo=20190402001019","trades":[],"_original_change_type":"신규"},{"ref_date":"20190425","obligation_date":"20190422","feed_date":"2019-07-03","change_type":"재진입","stake_pct":5.77,"stake_prev_pct":null,"stake_change":null,"ref_price":null,"total_buy_amount":0,"total_sell_amount":0,"net_amount":0,"trade_count":0,"dart_link":"https://dart.fss.or.kr/dsaf001/main.do?rcpNo=20190703000223","trades":[],"_original_change_type":"신규"},{"ref_date":"20190802","obligation_date":"20190802","feed_date":"2019-10-04","change_type":"재진입","stake_pct":4.66,"stake_prev_pct":null,"stake_change":null,"ref_price":null,"total_buy_amount":0,"total_sell_amount":0,"net_amount":0,"trade_count":0,"dart_link":"https://dart.fss.or.kr/dsaf001/main.do?rcpNo=20191004000147","trades":[],"_original_change_type":"신규"},{"ref_date":"20200909","obligation_date":"20200903","feed_date":"2020-10-06","change_type":"재진입","stake_pct":6.27,"stake_prev_pct":null,"stake_change":null,"ref_price":null,"total_buy_amount":0,"total_sell_amount":0,"net_amount":0,"trade_count":0,"dart_link":"https://dart.fss.or.kr/dsaf001/main.do?rcpNo=20201006000093","trades":[],"_original_change_type":"신규"},{"ref_date":"20201015","obligation_date":"20201015","feed_date":"2021-01-05","change_type":"재진입","stake_pct":7.29,"stake_prev_pct":null,"stake_change":null,"ref_price":null,"total_buy_amount":0,"total_sell_amount":0,"net_amount":0,"trade_count":0,"dart_link":"https://dart.fss.or.kr/dsaf001/main.do?rcpNo=20210105000237","trades":[],"_original_change_type":"신규"},{"ref_date":"20210312","obligation_date":"20210114","feed_date":"2021-04-05","change_type":"재진입","stake_pct":5.28,"stake_prev_pct":null,"stake_change":null,"ref_price":null,"total_buy_amount":0,"total_sell_amount":0,"net_amount":0,"trade_count":0,"dart_link":"https://dart.fss.or.kr/dsaf001/main.do?rcpNo=20210405002670","trades":[],"_original_change_type":"신규"},{"ref_date":"20210721","obligation_date":"20210721","feed_date":"2021-10-06","change_type":"재진입","stake_pct":4.26,"stake_prev_pct":null,"stake_change":null,"ref_price":null,"total_buy_amount":0,"total_sell_amount":0,"net_amount":0,"trade_count":0,"dart_link":"https://dart.fss.or.kr/dsaf001/main.do?rcpNo=20211006000445","trades":[],"_original_change_type":"신규"}]}