{"stock_code":"100840","stock_name":"SNT에너지","name_eng":"","sector":"","ceo":"","homepage":"","established":"","latest_per":null,"latest_pbr":null,"latest_roe":null,"latest_debt_ratio":null,"latest_ref_price":null,"fin_period":"","filing_count":13,"first_seen":"20171116","last_seen":"20260330","latest_stake_pct":5.18,"filings":[{"ref_date":"20171229","obligation_date":"20171116","feed_date":"2018-01-09","change_type":"증가","stake_pct":11.72,"stake_prev_pct":11.51,"stake_change":0.21000000000000085,"ref_price":null,"total_buy_amount":0,"total_sell_amount":0,"net_amount":0,"trade_count":0,"dart_link":"https://dart.fss.or.kr/dsaf001/main.do?rcpNo=20180109000116","trades":[]},{"ref_date":"20180330","obligation_date":"20180104","feed_date":"2018-04-06","change_type":"감소","stake_pct":10.8,"stake_prev_pct":11.72,"stake_change":-0.9199999999999999,"ref_price":null,"total_buy_amount":0,"total_sell_amount":0,"net_amount":0,"trade_count":0,"dart_link":"https://dart.fss.or.kr/dsaf001/main.do?rcpNo=20180406000554","trades":[]},{"ref_date":"20180629","obligation_date":"20180411","feed_date":"2018-07-06","change_type":"감소","stake_pct":10.63,"stake_prev_pct":10.8,"stake_change":-0.16999999999999993,"ref_price":null,"total_buy_amount":0,"total_sell_amount":0,"net_amount":0,"trade_count":0,"dart_link":"https://dart.fss.or.kr/dsaf001/main.do?rcpNo=20180706000037","trades":[]},{"ref_date":"20180823","obligation_date":"20180823","feed_date":"2018-10-04","change_type":"재진입","stake_pct":10.54,"stake_prev_pct":null,"stake_change":null,"ref_price":null,"total_buy_amount":0,"total_sell_amount":0,"net_amount":0,"trade_count":0,"dart_link":"https://dart.fss.or.kr/dsaf001/main.do?rcpNo=20181004000064","trades":[],"_original_change_type":"신규"},{"ref_date":"20180928","obligation_date":"20180824","feed_date":"2018-10-08","change_type":"감소","stake_pct":10.25,"stake_prev_pct":10.63,"stake_change":-0.3800000000000008,"ref_price":null,"total_buy_amount":0,"total_sell_amount":0,"net_amount":0,"trade_count":0,"dart_link":"https://dart.fss.or.kr/dsaf001/main.do?rcpNo=20181008000041","trades":[]},{"ref_date":"20181109","obligation_date":"20181016","feed_date":"2018-11-16","change_type":"감소","stake_pct":8.74,"stake_prev_pct":10.25,"stake_change":-1.5099999999999998,"ref_price":null,"total_buy_amount":0,"total_sell_amount":0,"net_amount":0,"trade_count":0,"dart_link":"https://dart.fss.or.kr/dsaf001/main.do?rcpNo=20181116000093","trades":[]},{"ref_date":"20181113","obligation_date":"20181107","feed_date":"2019-01-04","change_type":"재진입","stake_pct":7.4,"stake_prev_pct":null,"stake_change":null,"ref_price":null,"total_buy_amount":0,"total_sell_amount":0,"net_amount":0,"trade_count":0,"dart_link":"https://dart.fss.or.kr/dsaf001/main.do?rcpNo=20190104000059","trades":[],"_original_change_type":"신규"},{"ref_date":"20190201","obligation_date":"20190201","feed_date":"2019-04-02","change_type":"재진입","stake_pct":6.31,"stake_prev_pct":null,"stake_change":null,"ref_price":null,"total_buy_amount":0,"total_sell_amount":0,"net_amount":0,"trade_count":0,"dart_link":"https://dart.fss.or.kr/dsaf001/main.do?rcpNo=20190402000324","trades":[],"_original_change_type":"신규"},{"ref_date":"20191108","obligation_date":"20191108","feed_date":"2020-01-06","change_type":"재진입","stake_pct":5.11,"stake_prev_pct":null,"stake_change":null,"ref_price":null,"total_buy_amount":0,"total_sell_amount":0,"net_amount":0,"trade_count":0,"dart_link":"https://dart.fss.or.kr/dsaf001/main.do?rcpNo=20200106000051","trades":[],"_original_change_type":"신규"},{"ref_date":"20200310","obligation_date":"20200310","feed_date":"2020-04-03","change_type":"재진입","stake_pct":4.05,"stake_prev_pct":null,"stake_change":null,"ref_price":null,"total_buy_amount":0,"total_sell_amount":0,"net_amount":0,"trade_count":0,"dart_link":"https://dart.fss.or.kr/dsaf001/main.do?rcpNo=20200403000267","trades":[],"_original_change_type":"신규"},{"ref_date":"20241224","obligation_date":"20241224","feed_date":"2025-01-06","change_type":"재진입","stake_pct":5.16,"stake_prev_pct":null,"stake_change":null,"ref_price":null,"total_buy_amount":0,"total_sell_amount":0,"net_amount":0,"trade_count":0,"dart_link":"https://dart.fss.or.kr/dsaf001/main.do?rcpNo=20250106000111","trades":[],"_original_change_type":"신규"},{"ref_date":"20260102","obligation_date":"20251201","feed_date":"2026-01-02","change_type":"감소","stake_pct":4.07,"stake_prev_pct":5.16,"stake_change":-1.09,"ref_price":36050,"total_buy_amount":0,"total_sell_amount":8773116800,"net_amount":-8773116800,"trade_count":1,"dart_link":"https://dart.fss.or.kr/dsaf001/main.do?rcpNo=20260102000308","trades":[{"date":"20251201","reason":"Sell","shares_before":1066538,"shares_change":-223804,"shares_after":842734,"unit_price":39200,"note":"-","estimated":true}]},{"ref_date":"20260330","obligation_date":"20260330","feed_date":"2026-04-01","change_type":"재진입","stake_pct":5.18,"stake_prev_pct":null,"stake_change":null,"ref_price":null,"total_buy_amount":0,"total_sell_amount":0,"net_amount":0,"trade_count":0,"dart_link":"https://dart.fss.or.kr/dsaf001/main.do?rcpNo=20260401002407","trades":[],"_original_change_type":"신규"}]}